gdstore/__init__.py
gdstore/root.py
gdstore/store.py
gdstore/tree.py
gdstore-0.0.1.dist-info/LICENSE
gdstore-0.0.1.dist-info/WHEEL
gdstore-0.0.1.dist-info/METADATA
gdstore-0.0.1.dist-info/RECORD
