Metadata-Version: 2.1
Name: gdstore
Version: 0.0.1
Summary: simple data store using google drive
Author-email: oyajiDev <this.dev.somehit@gmail.com>
Requires-Python: >=3.9
Classifier: License :: OSI Approved :: MIT License
Classifier: Operating System :: POSIX
Classifier: Operating System :: MacOS :: MacOS X
Classifier: Operating System :: Microsoft :: Windows
Classifier: Programming Language :: Python :: 3
Classifier: Programming Language :: Python :: 3.9
Classifier: Programming Language :: Python :: 3.10
Classifier: Programming Language :: Python :: 3.11
Requires-Dist: google-api-python-client==2.97.0
Requires-Dist: google-auth-oauthlib==1.0.0
Requires-Dist: google-auth==2.22.0
Requires-Dist: gspread==5.10.0
Requires-Dist: tqdm==4.66.1
Requires-Dist: unix-os==0.4
Project-URL: repository, https://github.com/oyajiDev/gdstore
